LICENSE
MANIFEST.in
README.en.md
README.md
README.zh-cn.md
pyproject.toml
setup.cfg
setup.py
src/GetOptions/GetOptions.py
src/GetOptions/__init__.py
src/GetOptions.egg-info/PKG-INFO
src/GetOptions.egg-info/SOURCES.txt
src/GetOptions.egg-info/dependency_links.txt
src/GetOptions.egg-info/top_level.txt