Metadata-Version: 2.1
Name: GetOptions
Version: 1.0.2
Summary: Gets options from the console command
Home-page: https://github.com/thinkvue/GetOptions
Author: ThinkVue
Author-email: thinkvue@thinkvue.cn
License: UNKNOWN
Keywords: GET options Optional parameters GUN Unix Command Line
Platform: UNKNOWN
Classifier: Development Status :: 3 - Alpha
Classifier: Intended Audience :: Developers
Classifier: Topic :: Software Development :: Build Tools
Classifier: License :: OSI Approved :: MIT License
Classifier: Programming Language :: Python :: 3
Classifier: Programming Language :: Python :: 3.5
Classifier: Programming Language :: Python :: 3.6
Classifier: Programming Language :: Python :: 3.7
Classifier: Programming Language :: Python :: 3.8
Classifier: Programming Language :: Python :: 3 :: Only
Requires-Python: >=3.5, <4
